{"is_source_file": false, "format": null, "description": "", "external_files": [], "external_methods": [], "published": [], "classes": [], "methods": [], "calls": [], "search-terms": ["network-device-manager", "README.md", "network-device-manager-6144-6156"], "state": 2, "file_id": 6, "knowledge_revision": 8, "git_revision": "4e134ebbbb08bdb98d1a2dca897ffc559fc844c8", "hash": "0ab68cf0ae2e41afed388ef1192f41b5", "format-version": 4, "code-base-name": "backend", "filename": "README.md", "revision_history": [{"8": "4e134ebbbb08bdb98d1a2dca897ffc559fc844c8"}]}